gitcm/__init__.py
gitcm/main.py
gitcm-0.1.1.dist-info/METADATA
gitcm-0.1.1.dist-info/WHEEL
gitcm-0.1.1.dist-info/entry_points.txt
gitcm-0.1.1.dist-info/top_level.txt
gitcm-0.1.1.dist-info/RECORD
